{"Schedule":[{"description":"Qualification 1","tournamentLevel":"Qualification","matchNumber":1,"startTime":"2015-03-20T09:00:00","actualStartTime":"2015-03-20T09:01:53.347","scoreRedFinal":46,"scoreRedFoul":0,"scoreRedAuto":0,"scoreBlueFinal":10,"scoreBlueFoul":12,"scoreBlueAuto":0,"Teams":[{"teamNumber":4534,"station":"Red1","surrogate":false,"dq":false},{"teamNumber":2640,"station":"Red2","surrogate":false,"dq":false},{"teamNumber":5679,"station":"Red3","surrogate":false,"dq":false},{"teamNumber":3701,"station":"Blue1","surrogate":false,"dq":false},{"teamNumber":5511,"station":"Blue2","surrogate":false,"dq":false},{"teamNumber":3215,"station":"Blue3","surrogate":false,"dq":false}]},{"description":"Qualification 2","tournamentLevel":"Qualification","matchNumber":2,"startTime":"2015-03-20T09:07:00","actualStartTime":"2015-03-20T09:12:52.727","scoreRedFinal":24,"scoreRedFoul":0,"scoreRedAuto":0,"scoreBlueFinal":8,"scoreBlueFoul":0,"scoreBlueAuto":0,"Teams":[{"teamNumber":3680,"station":"Red1","surrogate":false,"dq":false},{"teamNumber":4996,"station":"Red2","surrogate":false,"dq":false},{"teamNumber":4533,"station":"Red3","surrogate":false,"dq":false},{"teamNumber":3796,"station":"Blue1","surrogate":false,"dq":false},{"teamNumber":4767,"station":"Blue2","surrogate":false,"dq":false},{"teamNumber":5727,"station":"Blue3","surrogate":false,"dq":false}]},{"description":"Qualification 3","tournamentLevel":"Qualification","matchNumber":3,"startTime":"2015-03-20T09:14:00","actualStartTime":"2015-03-20T09:20:09.227","scoreRedFinal":48,"scoreRedFoul":0,"scoreRedAuto":0,"scoreBlueFinal":62,"scoreBlueFoul":0,"scoreBlueAuto":0,"Teams":[{"teamNumber":2890,"station":"Red1","surrogate":false,"dq":false},{"teamNumber":587,"station":"Red2","surrogate":false,"dq":false},{"teamNumber":3402,"station":"Red3","surrogate":false,"dq":false},{"teamNumber":3661,"station":"Blue1","surrogate":false,"dq":false},{"teamNumber":3196,"station":"Blue2","surrogate":false,"dq":false},{"teamNumber":5543,"station":"Blue3","surrogate":false,"dq":false}]},{"description":"Qualification 4","tournamentLevel":"Qualification","matchNumber":4,"startTime":"2015-03-20T09:21:00","actualStartTime":"2015-03-20T09:27:50.39","scoreRedFinal":25,"scoreRedFoul":0,"scoreRedAuto":0,"scoreBlueFinal":4,"scoreBlueFoul":0,"scoreBlueAuto":0,"Teams":[{"teamNumber":4828,"station":"Red1","surrogate":false,"dq":false},{"teamNumber":2642,"station":"Red2","surrogate":false,"dq":false},{"teamNumber":4816,"station":"Red3","surrogate":false,"dq":false},{"teamNumber":435,"station":"Blue1","surrogate":false,"dq":false},{"teamNumber":4561,"station":"Blue2","surrogate":false,"dq":false},{"teamNumber":2641,"station":"Blue3","surrogate":false,"dq":false}]},{"description":"Qualification 5","tournamentLevel":"Qualification","matchNumber":5,"startTime":"2015-03-20T09:28:00","actualStartTime":"2015-03-20T09:34:21.537","scoreRedFinal":26,"scoreRedFoul":0,"scoreRedAuto":0,"scoreBlueFinal":30,"scoreBlueFoul":0,"scoreBlueAuto":0,"Teams":[{"teamNumber":4291,"station":"Red1","surrogate":false,"dq":false},{"teamNumber":3229,"station":"Red2","surrogate":false,"dq":false},{"teamNumber":5607,"station":"Red3","surrogate":false,"dq":false},{"teamNumber":3506,"station":"Blue1","surrogate":false,"dq":false},{"teamNumber":3336,"station":"Blue2","surrogate":false,"dq":false},{"teamNumber":4290,"station":"Blue3","surrogate":false,"dq":false}]},{"description":"Qualification 6","tournamentLevel":"Qualification","matchNumber":6,"startTime":"2015-03-20T09:35:00","actualStartTime":"2015-03-20T09:41:10.54","scoreRedFinal":62,"scoreRedFoul":0,"scoreRedAuto":0,"scoreBlueFinal":92,"scoreBlueFoul":0,"scoreBlueAuto":0,"Teams":[{"teamNumber":3737,"station":"Red1","surrogate":false,"dq":false},{"teamNumber":3763,"station":"Red2","surrogate":false,"dq":false},{"teamNumber":5518,"station":"Red3","surrogate":false,"dq":false},{"teamNumber":4073,"station":"Blue1","surrogate":false,"dq":false},{"teamNumber":5544,"station":"Blue2","surrogate":false,"dq":false},{"teamNumber":1225,"station":"Blue3","surrogate":false,"dq":false}]},{"description":"Qualification 7","tournamentLevel":"Qualification","matchNumber":7,"startTime":"2015-03-20T09:42:00","actualStartTime":"2015-03-20T09:47:49.49","scoreRedFinal":12,"scoreRedFoul":0,"scoreRedAuto":0,"scoreBlueFinal":15,"scoreBlueFoul":6,"scoreBlueAuto":0,"Teams":[{"teamNumber":3270,"station":"Red1","surrogate":false,"dq":false},{"teamNumber":5323,"station":"Red2","surrogate":false,"dq":false},{"teamNumber":3845,"station":"Red3","surrogate":false,"dq":false},{"teamNumber":2059,"station":"Blue1","surrogate":false,"dq":false},{"teamNumber":4795,"station":"Blue2","surrogate":false,"dq":false},{"teamNumber":2682,"station":"Blue3","surrogate":false,"dq":false}]},{"description":"Qualification 8","tournamentLevel":"Qualification","matchNumber":8,"startTime":"2015-03-20T09:49:00","actualStartTime":"2015-03-20T09:54:53.417","scoreRedFinal":47,"scoreRedFoul":0,"scoreRedAuto":0,"scoreBlueFinal":55,"scoreBlueFoul":0,"scoreBlueAuto":6,"Teams":[{"teamNumber":3971,"station":"Red1","surrogate":false,"dq":false},{"teamNumber":4829,"station":"Red2","surrogate":false,"dq":false},{"teamNumber":1413,"station":"Red3","surrogate":false,"dq":false},{"teamNumber":3331,"station":"Blue1","surrogate":false,"dq":false},{"teamNumber":1533,"station":"Blue2","surrogate":false,"dq":false},{"teamNumber":2528,"station":"Blue3","surrogate":false,"dq":false}]},{"description":"Qualification 9","tournamentLevel":"Qualification","matchNumber":9,"startTime":"2015-03-20T09:56:00","actualStartTime":"2015-03-20T10:01:43.843","scoreRedFinal":30,"scoreRedFoul":0,"scoreRedAuto":0,"scoreBlueFinal":0,"scoreBlueFoul":18,"scoreBlueAuto":0,"Teams":[{"teamNumber":5160,"station":"Red1","surrogate":false,"dq":false},{"teamNumber":900,"station":"Red2","surrogate":false,"dq":false},{"teamNumber":3459,"station":"Red3","surrogate":false,"dq":false},{"teamNumber":5762,"station":"Blue1","surrogate":false,"dq":false},{"teamNumber":5446,"station":"Blue2","surrogate":false,"dq":false},{"teamNumber":5190,"station":"Blue3","surrogate":false,"dq":false}]},{"description":"Qualification 10","tournamentLevel":"Qualification","matchNumber":10,"startTime":"2015-03-20T10:03:00","actualStartTime":"2015-03-20T10:09:00.05","scoreRedFinal":13,"scoreRedFoul":0,"scoreRedAuto":0,"scoreBlueFinal":5,"scoreBlueFoul":6,"scoreBlueAuto":0,"Teams":[{"teamNumber":3822,"station":"Red1","surrogate":false,"dq":false},{"teamNumber":3680,"station":"Red2","surrogate":false,"dq":false},{"teamNumber":5679,"station":"Red3","surrogate":false,"dq":false},{"teamNumber":3661,"station":"Blue1","surrogate":false,"dq":false},{"teamNumber":2890,"station":"Blue2","surrogate":false,"dq":false},{"teamNumber":4816,"station":"Blue3","surrogate":false,"dq":false}]},{"description":"Qualification 11","tournamentLevel":"Qualification","matchNumber":11,"startTime":"2015-03-20T10:15:00","actualStartTime":"2015-03-20T10:15:49.917","scoreRedFinal":9,"scoreRedFoul":0,"scoreRedAuto":0,"scoreBlueFinal":70,"scoreBlueFoul":0,"scoreBlueAuto":0,"Teams":[{"teamNumber":3763,"station":"Red1","surrogate":false,"dq":false},{"teamNumber":3196,"station":"Red2","surrogate":false,"dq":false},{"teamNumber":4767,"station":"Red3","surrogate":false,"dq":false},{"teamNumber":4828,"station":"Blue1","surrogate":false,"dq":false},{"teamNumber":5511,"station":"Blue2","surrogate":false,"dq":false},{"teamNumber":3506,"station":"Blue3","surrogate":false,"dq":false}]},{"description":"Qualification 12","tournamentLevel":"Qualification","matchNumber":12,"startTime":"2015-03-20T10:22:00","actualStartTime":"2015-03-20T10:22:50.483","scoreRedFinal":65,"scoreRedFoul":0,"scoreRedAuto":0,"scoreBlueFinal":17,"scoreBlueFoul":0,"scoreBlueAuto":0,"Teams":[{"teamNumber":1225,"station":"Red1","surrogate":false,"dq":false},{"teamNumber":4290,"station":"Red2","surrogate":false,"dq":false},{"teamNumber":3229,"station":"Red3","surrogate":false,"dq":false},{"teamNumber":2642,"station":"Blue1","surrogate":false,"dq":false},{"teamNumber":5543,"station":"Blue2","surrogate":false,"dq":false},{"teamNumber":2640,"station":"Blue3","surrogate":false,"dq":false}]},{"description":"Qualification 13","tournamentLevel":"Qualification","matchNumber":13,"startTime":"2015-03-20T10:29:00","actualStartTime":"2015-03-20T12:18:11.227","scoreRedFinal":32,"scoreRedFoul":0,"scoreRedAuto":0,"scoreBlueFinal":28,"scoreBlueFoul":0,"scoreBlueAuto":0,"Teams":[{"teamNumber":435,"station":"Red1","surrogate":false,"dq":false},{"teamNumber":3336,"station":"Red2","surrogate":false,"dq":false},{"teamNumber":4291,"station":"Red3","surrogate":false,"dq":false},{"teamNumber":3701,"station":"Blue1","surrogate":false,"dq":false},{"teamNumber":5323,"station":"Blue2","surrogate":false,"dq":false},{"teamNumber":5518,"station":"Blue3","surrogate":false,"dq":false}]},{"description":"Qualification 14","tournamentLevel":"Qualification","matchNumber":14,"startTime":"2015-03-20T10:36:00","actualStartTime":"2015-03-20T10:45:59.247","scoreRedFinal":20,"scoreRedFoul":0,"scoreRedAuto":0,"scoreBlueFinal":22,"scoreBlueFoul":0,"scoreBlueAuto":0,"Teams":[{"teamNumber":2641,"station":"Red1","surrogate":false,"dq":false},{"teamNumber":5544,"station":"Red2","surrogate":false,"dq":false},{"teamNumber":3796,"station":"Red3","surrogate":false,"dq":false},{"teamNumber":4996,"station":"Blue1","surrogate":false,"dq":false},{"teamNumber":3215,"station":"Blue2","surrogate":false,"dq":false},{"teamNumber":2059,"station":"Blue3","surrogate":false,"dq":false}]},{"description":"Qualification 15","tournamentLevel":"Qualification","matchNumber":15,"startTime":"2015-03-20T10:43:00","actualStartTime":"2015-03-20T10:53:16.787","scoreRedFinal":39,"scoreRedFoul":0,"scoreRedAuto":0,"scoreBlueFinal":10,"scoreBlueFoul":0,"scoreBlueAuto":0,"Teams":[{"teamNumber":3971,"station":"Red1","surrogate":false,"dq":false},{"teamNumber":3737,"station":"Red2","surrogate":false,"dq":false},{"teamNumber":5446,"station":"Red3","surrogate":false,"dq":false},{"teamNumber":1413,"station":"Blue1","surrogate":false,"dq":false},{"teamNumber":5727,"station":"Blue2","surrogate":false,"dq":false},{"teamNumber":4534,"station":"Blue3","surrogate":false,"dq":false}]},{"description":"Qualification 16","tournamentLevel":"Qualification","matchNumber":16,"startTime":"2015-03-20T10:50:00","actualStartTime":"2015-03-20T11:01:29.53","scoreRedFinal":20,"scoreRedFoul":6,"scoreRedAuto":0,"scoreBlueFinal":28,"scoreBlueFoul":0,"scoreBlueAuto":0,"Teams":[{"teamNumber":5190,"station":"Red1","surrogate":false,"dq":false},{"teamNumber":3402,"station":"Red2","surrogate":false,"dq":false},{"teamNumber":4073,"station":"Red3","surrogate":false,"dq":false},{"teamNumber":3822,"station":"Blue1","surrogate":false,"dq":false},{"teamNumber":5762,"station":"Blue2","surrogate":false,"dq":false},{"teamNumber":2682,"station":"Blue3","surrogate":false,"dq":false}]},{"description":"Qualification 17","tournamentLevel":"Qualification","matchNumber":17,"startTime":"2015-03-20T10:57:00","actualStartTime":"2015-03-20T11:07:55.717","scoreRedFinal":20,"scoreRedFoul":0,"scoreRedAuto":0,"scoreBlueFinal":21,"scoreBlueFoul":0,"scoreBlueAuto":0,"Teams":[{"teamNumber":4829,"station":"Red1","surrogate":false,"dq":false},{"teamNumber":4561,"station":"Red2","surrogate":false,"dq":false},{"teamNumber":3331,"station":"Red3","surrogate":false,"dq":false},{"teamNumber":5160,"station":"Blue1","surrogate":false,"dq":false},{"teamNumber":4795,"station":"Blue2","surrogate":false,"dq":false},{"teamNumber":3845,"station":"Blue3","surrogate":false,"dq":false}]},{"description":"Qualification 18","tournamentLevel":"Qualification","matchNumber":18,"startTime":"2015-03-20T11:04:00","actualStartTime":"2015-03-20T11:18:51.917","scoreRedFinal":34,"scoreRedFoul":6,"scoreRedAuto":0,"scoreBlueFinal":12,"scoreBlueFoul":0,"scoreBlueAuto":0,"Teams":[{"teamNumber":587,"station":"Red1","surrogate":false,"dq":false},{"teamNumber":3459,"station":"Red2","surrogate":false,"dq":false},{"teamNumber":4533,"station":"Red3","surrogate":false,"dq":false},{"teamNumber":3270,"station":"Blue1","surrogate":false,"dq":false},{"teamNumber":5607,"station":"Blue2","surrogate":false,"dq":false},{"teamNumber":900,"station":"Blue3","surrogate":false,"dq":false}]},{"description":"Qualification 19","tournamentLevel":"Qualification","matchNumber":19,"startTime":"2015-03-20T11:11:00","actualStartTime":"2015-03-20T11:25:11.67","scoreRedFinal":28,"scoreRedFoul":0,"scoreRedAuto":0,"scoreBlueFinal":12,"scoreBlueFoul":0,"scoreBlueAuto":0,"Teams":[{"teamNumber":1533,"station":"Red1","surrogate":false,"dq":false},{"teamNumber":3701,"station":"Red2","surrogate":false,"dq":false},{"teamNumber":4291,"station":"Red3","surrogate":false,"dq":false},{"teamNumber":2528,"station":"Blue1","surrogate":false,"dq":false},{"teamNumber":2059,"station":"Blue2","surrogate":false,"dq":false},{"teamNumber":4828,"station":"Blue3","surrogate":false,"dq":false}]},{"description":"Qualification 20","tournamentLevel":"Qualification","matchNumber":20,"startTime":"2015-03-20T11:18:00","actualStartTime":"2015-03-20T11:33:24.983","scoreRedFinal":55,"scoreRedFoul":0,"scoreRedAuto":0,"scoreBlueFinal":39,"scoreBlueFoul":0,"scoreBlueAuto":0,"Teams":[{"teamNumber":1225,"station":"Red1","surrogate":true,"dq":false},{"teamNumber":3215,"station":"Red2","surrogate":false,"dq":false},{"teamNumber":5446,"station":"Red3","surrogate":false,"dq":false},{"teamNumber":3336,"station":"Blue1","surrogate":true,"dq":false},{"teamNumber":3196,"station":"Blue2","surrogate":false,"dq":false},{"teamNumber":4816,"station":"Blue3","surrogate":false,"dq":false}]},{"description":"Qualification 21","tournamentLevel":"Qualification","matchNumber":21,"startTime":"2015-03-20T11:30:00","actualStartTime":"2015-03-20T11:39:48.15","scoreRedFinal":34,"scoreRedFoul":0,"scoreRedAuto":0,"scoreBlueFinal":13,"scoreBlueFoul":0,"scoreBlueAuto":0,"Teams":[{"teamNumber":4534,"station":"Red1","surrogate":false,"dq":false},{"teamNumber":5762,"station":"Red2","surrogate":false,"dq":false},{"teamNumber":4073,"station":"Red3","surrogate":false,"dq":false},{"teamNumber":2890,"station":"Blue1","surrogate":false,"dq":false},{"teamNumber":5543,"station":"Blue2","surrogate":false,"dq":false},{"teamNumber":5727,"station":"Blue3","surrogate":false,"dq":false}]},{"description":"Qualification 22","tournamentLevel":"Qualification","matchNumber":22,"startTime":"2015-03-20T11:37:00","actualStartTime":"2015-03-20T11:51:11.793","scoreRedFinal":45,"scoreRedFoul":0,"scoreRedAuto":0,"scoreBlueFinal":10,"scoreBlueFoul":0,"scoreBlueAuto":0,"Teams":[{"teamNumber":3971,"station":"Red1","surrogate":false,"dq":false},{"teamNumber":5518,"station":"Red2","surrogate":false,"dq":false},{"teamNumber":2641,"station":"Red3","surrogate":false,"dq":false},{"teamNumber":4767,"station":"Blue1","surrogate":false,"dq":false},{"teamNumber":1413,"station":"Blue2","surrogate":false,"dq":false},{"teamNumber":4795,"station":"Blue3","surrogate":false,"dq":false}]},{"description":"Qualification 23","tournamentLevel":"Qualification","matchNumber":23,"startTime":"2015-03-20T11:44:00","actualStartTime":"2015-03-20T11:57:48.213","scoreRedFinal":33,"scoreRedFoul":0,"scoreRedAuto":0,"scoreBlueFinal":29,"scoreBlueFoul":0,"scoreBlueAuto":0,"Teams":[{"teamNumber":4561,"station":"Red1","surrogate":false,"dq":false},{"teamNumber":4290,"station":"Red2","surrogate":false,"dq":false},{"teamNumber":3459,"station":"Red3","surrogate":false,"dq":false},{"teamNumber":3796,"station":"Blue1","surrogate":false,"dq":false},{"teamNumber":5679,"station":"Blue2","surrogate":false,"dq":false},{"teamNumber":5323,"station":"Blue3","surrogate":false,"dq":false}]},{"description":"Qualification 24","tournamentLevel":"Qualification","matchNumber":24,"startTime":"2015-03-20T11:51:00","actualStartTime":"2015-03-20T12:04:31.88","scoreRedFinal":60,"scoreRedFoul":0,"scoreRedAuto":0,"scoreBlueFinal":30,"scoreBlueFoul":0,"scoreBlueAuto":0,"Teams":[{"teamNumber":587,"station":"Red1","surrogate":false,"dq":false},{"teamNumber":4996,"station":"Red2","surrogate":false,"dq":false},{"teamNumber":3763,"station":"Red3","surrogate":false,"dq":false},{"teamNumber":2682,"station":"Blue1","surrogate":false,"dq":false},{"teamNumber":2642,"station":"Blue2","surrogate":false,"dq":false},{"teamNumber":3680,"station":"Blue3","surrogate":false,"dq":false}]},{"description":"Qualification 25","tournamentLevel":"Qualification","matchNumber":25,"startTime":"2015-03-20T11:58:00","actualStartTime":"2015-03-20T12:11:51.027","scoreRedFinal":50,"scoreRedFoul":0,"scoreRedAuto":0,"scoreBlueFinal":35,"scoreBlueFoul":6,"scoreBlueAuto":0,"Teams":[{"teamNumber":3402,"station":"Red1","surrogate":false,"dq":false},{"teamNumber":3822,"station":"Red2","surrogate":false,"dq":false},{"teamNumber":5160,"station":"Red3","surrogate":false,"dq":false},{"teamNumber":2640,"station":"Blue1","surrogate":false,"dq":false},{"teamNumber":900,"station":"Blue2","surrogate":false,"dq":false},{"teamNumber":3737,"station":"Blue3","surrogate":false,"dq":false}]},{"description":"Qualification 26","tournamentLevel":"Qualification","matchNumber":26,"startTime":"2015-03-20T13:10:00","actualStartTime":"2015-03-20T13:20:11.553","scoreRedFinal":36,"scoreRedFoul":0,"scoreRedAuto":0,"scoreBlueFinal":2,"scoreBlueFoul":0,"scoreBlueAuto":0,"Teams":[{"teamNumber":3331,"station":"Red1","surrogate":false,"dq":false},{"teamNumber":3229,"station":"Red2","surrogate":false,"dq":false},{"teamNumber":5544,"station":"Red3","surrogate":false,"dq":false},{"teamNumber":3270,"station":"Blue1","surrogate":false,"dq":false},{"teamNumber":4533,"station":"Blue2","surrogate":false,"dq":false},{"teamNumber":4829,"station":"Blue3","surrogate":false,"dq":false}]},{"description":"Qualification 27","tournamentLevel":"Qualification","matchNumber":27,"startTime":"2015-03-20T13:17:00","actualStartTime":"2015-03-20T13:26:46.71","scoreRedFinal":77,"scoreRedFoul":0,"scoreRedAuto":0,"scoreBlueFinal":41,"scoreBlueFoul":6,"scoreBlueAuto":0,"Teams":[{"teamNumber":5607,"station":"Red1","surrogate":false,"dq":false},{"teamNumber":3506,"station":"Red2","surrogate":false,"dq":false},{"teamNumber":1533,"station":"Red3","surrogate":false,"dq":false},{"teamNumber":5511,"station":"Blue1","surrogate":false,"dq":false},{"teamNumber":5190,"station":"Blue2","surrogate":false,"dq":false},{"teamNumber":3845,"station":"Blue3","surrogate":false,"dq":false}]},{"description":"Qualification 28","tournamentLevel":"Qualification","matchNumber":28,"startTime":"2015-03-20T13:24:00","actualStartTime":"2015-03-20T13:33:41.693","scoreRedFinal":0,"scoreRedFoul":18,"scoreRedAuto":0,"scoreBlueFinal":32,"scoreBlueFoul":0,"scoreBlueAuto":0,"Teams":[{"teamNumber":3661,"station":"Red1","surrogate":false,"dq":false},{"teamNumber":2528,"station":"Red2","surrogate":false,"dq":false},{"teamNumber":3459,"station":"Red3","surrogate":false,"dq":false},{"teamNumber":435,"station":"Blue1","surrogate":false,"dq":false},{"teamNumber":1225,"station":"Blue2","surrogate":false,"dq":false},{"teamNumber":5518,"station":"Blue3","surrogate":false,"dq":false}]},{"description":"Qualification 29","tournamentLevel":"Qualification","matchNumber":29,"startTime":"2015-03-20T13:31:00","actualStartTime":"2015-03-20T13:41:52.07","scoreRedFinal":18,"scoreRedFoul":0,"scoreRedAuto":0,"scoreBlueFinal":0,"scoreBlueFoul":6,"scoreBlueAuto":0,"Teams":[{"teamNumber":3196,"station":"Red1","surrogate":false,"dq":false},{"teamNumber":5446,"station":"Red2","surrogate":false,"dq":false},{"teamNumber":3680,"station":"Red3","surrogate":false,"dq":false},{"teamNumber":5762,"station":"Blue1","surrogate":false,"dq":false},{"teamNumber":3701,"station":"Blue2","surrogate":false,"dq":false},{"teamNumber":4290,"station":"Blue3","surrogate":false,"dq":false}]},{"description":"Qualification 30","tournamentLevel":"Qualification","matchNumber":30,"startTime":"2015-03-20T13:38:00","actualStartTime":"2015-03-20T13:48:13.94","scoreRedFinal":60,"scoreRedFoul":0,"scoreRedAuto":0,"scoreBlueFinal":25,"scoreBlueFoul":0,"scoreBlueAuto":0,"Teams":[{"teamNumber":2642,"station":"Red1","surrogate":false,"dq":false},{"teamNumber":4073,"station":"Red2","surrogate":false,"dq":false},{"teamNumber":2059,"station":"Red3","surrogate":false,"dq":false},{"teamNumber":5679,"station":"Blue1","surrogate":false,"dq":false},{"teamNumber":900,"station":"Blue2","surrogate":false,"dq":false},{"teamNumber":4795,"station":"Blue3","surrogate":false,"dq":false}]},{"description":"Qualification 31","tournamentLevel":"Qualification","matchNumber":31,"startTime":"2015-03-20T13:45:00","actualStartTime":"2015-03-20T14:09:17.98","scoreRedFinal":26,"scoreRedFoul":0,"scoreRedAuto":0,"scoreBlueFinal":2,"scoreBlueFoul":6,"scoreBlueAuto":0,"Teams":[{"teamNumber":5727,"station":"Red1","surrogate":false,"dq":false},{"teamNumber":3215,"station":"Red2","surrogate":false,"dq":false},{"teamNumber":3971,"station":"Red3","surrogate":false,"dq":false},{"teamNumber":5323,"station":"Blue1","surrogate":false,"dq":false},{"teamNumber":3402,"station":"Blue2","surrogate":false,"dq":false},{"teamNumber":3229,"station":"Blue3","surrogate":false,"dq":false}]},{"description":"Qualification 32","tournamentLevel":"Qualification","matchNumber":32,"startTime":"2015-03-20T13:52:00","actualStartTime":"2015-03-20T14:15:56.34","scoreRedFinal":27,"scoreRedFoul":0,"scoreRedAuto":0,"scoreBlueFinal":24,"scoreBlueFoul":0,"scoreBlueAuto":0,"Teams":[{"teamNumber":3845,"station":"Red1","surrogate":false,"dq":false},{"teamNumber":4996,"station":"Red2","surrogate":false,"dq":false},{"teamNumber":3796,"station":"Red3","surrogate":false,"dq":false},{"teamNumber":3763,"station":"Blue1","surrogate":false,"dq":false},{"teamNumber":3822,"station":"Blue2","surrogate":false,"dq":false},{"teamNumber":4291,"station":"Blue3","surrogate":false,"dq":false}]},{"description":"Qualification 33","tournamentLevel":"Qualification","matchNumber":33,"startTime":"2015-03-20T13:59:00","actualStartTime":"2015-03-20T14:21:38.86","scoreRedFinal":48,"scoreRedFoul":6,"scoreRedAuto":0,"scoreBlueFinal":58,"scoreBlueFoul":0,"scoreBlueAuto":0,"Teams":[{"teamNumber":5190,"station":"Red1","surrogate":false,"dq":false},{"teamNumber":5160,"station":"Red2","surrogate":false,"dq":false},{"teamNumber":2682,"station":"Red3","surrogate":false,"dq":false},{"teamNumber":3661,"station":"Blue1","surrogate":false,"dq":false},{"teamNumber":4828,"station":"Blue2","surrogate":false,"dq":false},{"teamNumber":3336,"station":"Blue3","surrogate":false,"dq":false}]},{"description":"Qualification 34","tournamentLevel":"Qualification","matchNumber":34,"startTime":"2015-03-20T14:06:00","actualStartTime":"2015-03-20T14:28:28.22","scoreRedFinal":32,"scoreRedFoul":0,"scoreRedAuto":0,"scoreBlueFinal":20,"scoreBlueFoul":0,"scoreBlueAuto":4,"Teams":[{"teamNumber":1533,"station":"Red1","surrogate":false,"dq":false},{"teamNumber":4767,"station":"Red2","surrogate":false,"dq":false},{"teamNumber":435,"station":"Red3","surrogate":false,"dq":false},{"teamNumber":5544,"station":"Blue1","surrogate":false,"dq":false},{"teamNumber":4534,"station":"Blue2","surrogate":false,"dq":false},{"teamNumber":3737,"station":"Blue3","surrogate":false,"dq":false}]},{"description":"Qualification 35","tournamentLevel":"Qualification","matchNumber":35,"startTime":"2015-03-20T14:13:00","actualStartTime":"2015-03-20T14:34:37.253","scoreRedFinal":53,"scoreRedFoul":0,"scoreRedAuto":0,"scoreBlueFinal":20,"scoreBlueFoul":0,"scoreBlueAuto":0,"Teams":[{"teamNumber":5607,"station":"Red1","surrogate":false,"dq":false},{"teamNumber":2641,"station":"Red2","surrogate":false,"dq":false},{"teamNumber":5511,"station":"Red3","surrogate":false,"dq":false},{"teamNumber":3331,"station":"Blue1","surrogate":false,"dq":false},{"teamNumber":5543,"station":"Blue2","surrogate":false,"dq":false},{"teamNumber":587,"station":"Blue3","surrogate":false,"dq":false}]},{"description":"Qualification 36","tournamentLevel":"Qualification","matchNumber":36,"startTime":"2015-03-20T14:20:00","actualStartTime":"2015-03-20T14:40:58.397","scoreRedFinal":56,"scoreRedFoul":0,"scoreRedAuto":0,"scoreBlueFinal":83,"scoreBlueFoul":0,"scoreBlueAuto":0,"Teams":[{"teamNumber":1413,"station":"Red1","surrogate":false,"dq":false},{"teamNumber":2528,"station":"Red2","surrogate":false,"dq":false},{"teamNumber":3506,"station":"Red3","surrogate":false,"dq":false},{"teamNumber":4533,"station":"Blue1","surrogate":false,"dq":false},{"teamNumber":4561,"station":"Blue2","surrogate":false,"dq":false},{"teamNumber":2640,"station":"Blue3","surrogate":false,"dq":false}]},{"description":"Qualification 37","tournamentLevel":"Qualification","matchNumber":37,"startTime":"2015-03-20T14:27:00","actualStartTime":"2015-03-20T14:47:03.073","scoreRedFinal":50,"scoreRedFoul":6,"scoreRedAuto":0,"scoreBlueFinal":53,"scoreBlueFoul":0,"scoreBlueAuto":0,"Teams":[{"teamNumber":3270,"station":"Red1","surrogate":false,"dq":false},{"teamNumber":2890,"station":"Red2","surrogate":false,"dq":false},{"teamNumber":4996,"station":"Red3","surrogate":false,"dq":false},{"teamNumber":4816,"station":"Blue1","surrogate":false,"dq":false},{"teamNumber":4829,"station":"Blue2","surrogate":false,"dq":false},{"teamNumber":5446,"station":"Blue3","surrogate":false,"dq":false}]},{"description":"Qualification 38","tournamentLevel":"Qualification","matchNumber":38,"startTime":"2015-03-20T14:34:00","actualStartTime":"2015-03-20T14:54:37.623","scoreRedFinal":27,"scoreRedFoul":0,"scoreRedAuto":0,"scoreBlueFinal":28,"scoreBlueFoul":0,"scoreBlueAuto":0,"Teams":[{"teamNumber":900,"station":"Red1","surrogate":false,"dq":false},{"teamNumber":5323,"station":"Red2","surrogate":false,"dq":false},{"teamNumber":3661,"station":"Red3","surrogate":false,"dq":false},{"teamNumber":4828,"station":"Blue1","surrogate":false,"dq":false},{"teamNumber":3229,"station":"Blue2","surrogate":false,"dq":false},{"teamNumber":3796,"station":"Blue3","surrogate":false,"dq":false}]},{"description":"Qualification 39","tournamentLevel":"Qualification","matchNumber":39,"startTime":"2015-03-20T14:41:00","actualStartTime":"2015-03-20T15:00:37.567","scoreRedFinal":67,"scoreRedFoul":0,"scoreRedAuto":0,"scoreBlueFinal":54,"scoreBlueFoul":0,"scoreBlueAuto":0,"Teams":[{"teamNumber":4290,"station":"Red1","surrogate":false,"dq":false},{"teamNumber":4073,"station":"Red2","surrogate":false,"dq":false},{"teamNumber":5727,"station":"Red3","surrogate":false,"dq":false},{"teamNumber":3701,"station":"Blue1","surrogate":false,"dq":false},{"teamNumber":3336,"station":"Blue2","surrogate":false,"dq":false},{"teamNumber":3459,"station":"Blue3","surrogate":false,"dq":false}]},{"description":"Qualification 40","tournamentLevel":"Qualification","matchNumber":40,"startTime":"2015-03-20T14:48:00","actualStartTime":"2015-03-20T15:07:01.693","scoreRedFinal":10,"scoreRedFoul":0,"scoreRedAuto":0,"scoreBlueFinal":42,"scoreBlueFoul":0,"scoreBlueAuto":0,"Teams":[{"teamNumber":3845,"station":"Red1","surrogate":false,"dq":false},{"teamNumber":5679,"station":"Red2","surrogate":false,"dq":false},{"teamNumber":5607,"station":"Red3","surrogate":false,"dq":false},{"teamNumber":4767,"station":"Blue1","surrogate":false,"dq":false},{"teamNumber":1225,"station":"Blue2","surrogate":false,"dq":false},{"teamNumber":4534,"station":"Blue3","surrogate":false,"dq":false}]},{"description":"Qualification 41","tournamentLevel":"Qualification","matchNumber":41,"startTime":"2015-03-20T14:55:00","actualStartTime":"2015-03-20T15:14:26.267","scoreRedFinal":4,"scoreRedFoul":0,"scoreRedAuto":0,"scoreBlueFinal":24,"scoreBlueFoul":0,"scoreBlueAuto":0,"Teams":[{"teamNumber":5160,"station":"Red1","surrogate":false,"dq":false},{"teamNumber":3215,"station":"Red2","surrogate":false,"dq":false},{"teamNumber":4291,"station":"Red3","surrogate":false,"dq":false},{"teamNumber":1413,"station":"Blue1","surrogate":false,"dq":false},{"teamNumber":1533,"station":"Blue2","surrogate":false,"dq":false},{"teamNumber":587,"station":"Blue3","surrogate":false,"dq":false}]},{"description":"Qualification 42","tournamentLevel":"Qualification","matchNumber":42,"startTime":"2015-03-20T15:02:00","actualStartTime":"2015-03-20T15:20:03.777","scoreRedFinal":67,"scoreRedFoul":0,"scoreRedAuto":0,"scoreBlueFinal":50,"scoreBlueFoul":0,"scoreBlueAuto":0,"Teams":[{"teamNumber":3506,"station":"Red1","surrogate":false,"dq":false},{"teamNumber":3270,"station":"Red2","surrogate":false,"dq":false},{"teamNumber":5543,"station":"Red3","surrogate":false,"dq":false},{"teamNumber":435,"station":"Blue1","surrogate":false,"dq":false},{"teamNumber":3822,"station":"Blue2","surrogate":false,"dq":false},{"teamNumber":3971,"station":"Blue3","surrogate":false,"dq":false}]},{"description":"Qualification 43","tournamentLevel":"Qualification","matchNumber":43,"startTime":"2015-03-20T15:09:00","actualStartTime":"2015-03-20T15:27:16.453","scoreRedFinal":57,"scoreRedFoul":0,"scoreRedAuto":0,"scoreBlueFinal":74,"scoreBlueFoul":0,"scoreBlueAuto":0,"Teams":[{"teamNumber":3196,"station":"Red1","surrogate":false,"dq":false},{"teamNumber":2682,"station":"Red2","surrogate":false,"dq":false},{"teamNumber":3737,"station":"Red3","surrogate":false,"dq":false},{"teamNumber":4533,"station":"Blue1","surrogate":false,"dq":false},{"teamNumber":2641,"station":"Blue2","surrogate":false,"dq":false},{"teamNumber":2528,"station":"Blue3","surrogate":false,"dq":false}]},{"description":"Qualification 44","tournamentLevel":"Qualification","matchNumber":44,"startTime":"2015-03-20T15:16:00","actualStartTime":"2015-03-20T15:34:11.883","scoreRedFinal":6,"scoreRedFoul":0,"scoreRedAuto":0,"scoreBlueFinal":12,"scoreBlueFoul":0,"scoreBlueAuto":0,"Teams":[{"teamNumber":4795,"station":"Red1","surrogate":false,"dq":false},{"teamNumber":4561,"station":"Red2","surrogate":false,"dq":false},{"teamNumber":5544,"station":"Red3","surrogate":false,"dq":false},{"teamNumber":3680,"station":"Blue1","surrogate":false,"dq":false},{"teamNumber":2640,"station":"Blue2","surrogate":false,"dq":false},{"teamNumber":5190,"station":"Blue3","surrogate":false,"dq":false}]},{"description":"Qualification 45","tournamentLevel":"Qualification","matchNumber":45,"startTime":"2015-03-20T15:23:00","actualStartTime":"2015-03-20T15:41:15","scoreRedFinal":10,"scoreRedFoul":0,"scoreRedAuto":0,"scoreBlueFinal":26,"scoreBlueFoul":0,"scoreBlueAuto":0,"Teams":[{"teamNumber":5762,"station":"Red1","surrogate":false,"dq":false},{"teamNumber":3402,"station":"Red2","surrogate":false,"dq":false},{"teamNumber":4816,"station":"Red3","surrogate":false,"dq":false},{"teamNumber":2059,"station":"Blue1","surrogate":false,"dq":false},{"teamNumber":3763,"station":"Blue2","surrogate":false,"dq":false},{"teamNumber":3331,"station":"Blue3","surrogate":false,"dq":false}]},{"description":"Qualification 46","tournamentLevel":"Qualification","matchNumber":46,"startTime":"2015-03-20T15:30:00","actualStartTime":"2015-03-20T15:52:14.1","scoreRedFinal":8,"scoreRedFoul":6,"scoreRedAuto":0,"scoreBlueFinal":44,"scoreBlueFoul":0,"scoreBlueAuto":0,"Teams":[{"teamNumber":2890,"station":"Red1","surrogate":false,"dq":false},{"teamNumber":4829,"station":"Red2","surrogate":false,"dq":false},{"teamNumber":2642,"station":"Red3","surrogate":false,"dq":false},{"teamNumber":5518,"station":"Blue1","surrogate":false,"dq":false},{"teamNumber":5511,"station":"Blue2","surrogate":false,"dq":false},{"teamNumber":3796,"station":"Blue3","surrogate":false,"dq":false}]},{"description":"Qualification 47","tournamentLevel":"Qualification","matchNumber":47,"startTime":"2015-03-20T15:37:00","actualStartTime":"2015-03-20T15:58:21.28","scoreRedFinal":36,"scoreRedFoul":0,"scoreRedAuto":0,"scoreBlueFinal":35,"scoreBlueFoul":0,"scoreBlueAuto":0,"Teams":[{"teamNumber":5446,"station":"Red1","surrogate":false,"dq":false},{"teamNumber":5323,"station":"Red2","surrogate":false,"dq":false},{"teamNumber":3336,"station":"Red3","surrogate":false,"dq":false},{"teamNumber":1533,"station":"Blue1","surrogate":false,"dq":false},{"teamNumber":5543,"station":"Blue2","surrogate":false,"dq":false},{"teamNumber":5679,"station":"Blue3","surrogate":false,"dq":false}]},{"description":"Qualification 48","tournamentLevel":"Qualification","matchNumber":48,"startTime":"2015-03-20T15:44:00","actualStartTime":"2015-03-20T16:04:45.903","scoreRedFinal":23,"scoreRedFoul":0,"scoreRedAuto":0,"scoreBlueFinal":42,"scoreBlueFoul":0,"scoreBlueAuto":0,"Teams":[{"teamNumber":3661,"station":"Red1","surrogate":false,"dq":false},{"teamNumber":1225,"station":"Red2","surrogate":false,"dq":false},{"teamNumber":3506,"station":"Red3","surrogate":false,"dq":false},{"teamNumber":4073,"station":"Blue1","surrogate":false,"dq":false},{"teamNumber":900,"station":"Blue2","surrogate":false,"dq":false},{"teamNumber":2641,"station":"Blue3","surrogate":false,"dq":false}]},{"description":"Qualification 49","tournamentLevel":"Qualification","matchNumber":49,"startTime":"2015-03-20T15:51:00","actualStartTime":"2015-03-20T16:11:48.307","scoreRedFinal":8,"scoreRedFoul":0,"scoreRedAuto":0,"scoreBlueFinal":24,"scoreBlueFoul":0,"scoreBlueAuto":0,"Teams":[{"teamNumber":3701,"station":"Red1","surrogate":false,"dq":false},{"teamNumber":3229,"station":"Red2","surrogate":false,"dq":false},{"teamNumber":5190,"station":"Red3","surrogate":false,"dq":false},{"teamNumber":4561,"station":"Blue1","surrogate":false,"dq":false},{"teamNumber":3737,"station":"Blue2","surrogate":false,"dq":false},{"teamNumber":4996,"station":"Blue3","surrogate":false,"dq":false}]},{"description":"Qualification 50","tournamentLevel":"Qualification","matchNumber":50,"startTime":"2015-03-20T15:58:00","actualStartTime":"2015-03-20T16:18:36.29","scoreRedFinal":57,"scoreRedFoul":0,"scoreRedAuto":0,"scoreBlueFinal":58,"scoreBlueFoul":0,"scoreBlueAuto":4,"Teams":[{"teamNumber":4795,"station":"Red1","surrogate":false,"dq":false},{"teamNumber":3459,"station":"Red2","surrogate":false,"dq":false},{"teamNumber":3196,"station":"Red3","surrogate":false,"dq":false},{"teamNumber":4534,"station":"Blue1","surrogate":false,"dq":false},{"teamNumber":2682,"station":"Blue2","surrogate":false,"dq":false},{"teamNumber":4291,"station":"Blue3","surrogate":false,"dq":false}]},{"description":"Qualification 51","tournamentLevel":"Qualification","matchNumber":51,"startTime":"2015-03-20T16:05:00","actualStartTime":"2015-03-20T16:25:42.487","scoreRedFinal":129,"scoreRedFoul":0,"scoreRedAuto":0,"scoreBlueFinal":93,"scoreBlueFoul":0,"scoreBlueAuto":4,"Teams":[{"teamNumber":2059,"station":"Red1","surrogate":false,"dq":false},{"teamNumber":3971,"station":"Red2","surrogate":false,"dq":false},{"teamNumber":5160,"station":"Red3","surrogate":false,"dq":false},{"teamNumber":5511,"station":"Blue1","surrogate":false,"dq":false},{"teamNumber":4533,"station":"Blue2","surrogate":false,"dq":false},{"teamNumber":2642,"station":"Blue3","surrogate":false,"dq":false}]},{"description":"Qualification 52","tournamentLevel":"Qualification","matchNumber":52,"startTime":"2015-03-20T16:12:00","actualStartTime":"2015-03-20T16:32:19.5","scoreRedFinal":18,"scoreRedFoul":0,"scoreRedAuto":0,"scoreBlueFinal":26,"scoreBlueFoul":0,"scoreBlueAuto":0,"Teams":[{"teamNumber":435,"station":"Red1","surrogate":false,"dq":false},{"teamNumber":4816,"station":"Red2","surrogate":false,"dq":false},{"teamNumber":587,"station":"Red3","surrogate":false,"dq":false},{"teamNumber":1413,"station":"Blue1","surrogate":false,"dq":false},{"teamNumber":4290,"station":"Blue2","surrogate":false,"dq":false},{"teamNumber":3845,"station":"Blue3","surrogate":false,"dq":false}]},{"description":"Qualification 53","tournamentLevel":"Qualification","matchNumber":53,"startTime":"2015-03-20T16:19:00","actualStartTime":"2015-03-20T16:38:10.867","scoreRedFinal":20,"scoreRedFoul":0,"scoreRedAuto":0,"scoreBlueFinal":58,"scoreBlueFoul":0,"scoreBlueAuto":0,"Teams":[{"teamNumber":5727,"station":"Red1","surrogate":false,"dq":false},{"teamNumber":3331,"station":"Red2","surrogate":false,"dq":false},{"teamNumber":5762,"station":"Red3","surrogate":false,"dq":false},{"teamNumber":3822,"station":"Blue1","surrogate":false,"dq":false},{"teamNumber":5544,"station":"Blue2","surrogate":false,"dq":false},{"teamNumber":4828,"station":"Blue3","surrogate":false,"dq":false}]},{"description":"Qualification 54","tournamentLevel":"Qualification","matchNumber":54,"startTime":"2015-03-20T16:26:00","actualStartTime":"2015-03-20T16:44:25.003","scoreRedFinal":4,"scoreRedFoul":0,"scoreRedAuto":0,"scoreBlueFinal":12,"scoreBlueFoul":0,"scoreBlueAuto":0,"Teams":[{"teamNumber":2640,"station":"Red1","surrogate":false,"dq":false},{"teamNumber":4767,"station":"Red2","surrogate":false,"dq":false},{"teamNumber":2890,"station":"Red3","surrogate":false,"dq":false},{"teamNumber":2528,"station":"Blue1","surrogate":false,"dq":false},{"teamNumber":3763,"station":"Blue2","surrogate":false,"dq":false},{"teamNumber":4829,"station":"Blue3","surrogate":false,"dq":false}]},{"description":"Qualification 55","tournamentLevel":"Qualification","matchNumber":55,"startTime":"2015-03-20T16:33:00","actualStartTime":"2015-03-20T16:50:34.707","scoreRedFinal":19,"scoreRedFoul":0,"scoreRedAuto":0,"scoreBlueFinal":23,"scoreBlueFoul":0,"scoreBlueAuto":0,"Teams":[{"teamNumber":3680,"station":"Red1","surrogate":false,"dq":false},{"teamNumber":3270,"station":"Red2","surrogate":false,"dq":false},{"teamNumber":5518,"station":"Red3","surrogate":false,"dq":false},{"teamNumber":3402,"station":"Blue1","surrogate":false,"dq":false},{"teamNumber":5607,"station":"Blue2","surrogate":false,"dq":false},{"teamNumber":3215,"station":"Blue3","surrogate":false,"dq":false}]},{"description":"Qualification 56","tournamentLevel":"Qualification","matchNumber":56,"startTime":"2015-03-20T16:40:00","actualStartTime":"2015-03-20T16:57:16.527","scoreRedFinal":55,"scoreRedFoul":0,"scoreRedAuto":0,"scoreBlueFinal":44,"scoreBlueFoul":0,"scoreBlueAuto":0,"Teams":[{"teamNumber":5511,"station":"Red1","surrogate":false,"dq":false},{"teamNumber":4291,"station":"Red2","surrogate":false,"dq":false},{"teamNumber":4561,"station":"Red3","surrogate":false,"dq":false},{"teamNumber":4533,"station":"Blue1","surrogate":false,"dq":false},{"teamNumber":4073,"station":"Blue2","surrogate":false,"dq":false},{"teamNumber":3661,"station":"Blue3","surrogate":false,"dq":false}]},{"description":"Qualification 57","tournamentLevel":"Qualification","matchNumber":57,"startTime":"2015-03-20T16:47:00","actualStartTime":"2015-03-20T17:03:23.813","scoreRedFinal":58,"scoreRedFoul":0,"scoreRedAuto":0,"scoreBlueFinal":23,"scoreBlueFoul":0,"scoreBlueAuto":0,"Teams":[{"teamNumber":3796,"station":"Red1","surrogate":false,"dq":false},{"teamNumber":4816,"station":"Red2","surrogate":false,"dq":false},{"teamNumber":1225,"station":"Red3","surrogate":false,"dq":false},{"teamNumber":3971,"station":"Blue1","surrogate":false,"dq":false},{"teamNumber":3701,"station":"Blue2","surrogate":false,"dq":false},{"teamNumber":2682,"station":"Blue3","surrogate":false,"dq":false}]},{"description":"Qualification 58","tournamentLevel":"Qualification","matchNumber":58,"startTime":"2015-03-20T16:54:00","actualStartTime":"2015-03-20T17:09:23.977","scoreRedFinal":48,"scoreRedFoul":0,"scoreRedAuto":4,"scoreBlueFinal":0,"scoreBlueFoul":12,"scoreBlueAuto":0,"Teams":[{"teamNumber":900,"station":"Red1","surrogate":false,"dq":false},{"teamNumber":5544,"station":"Red2","surrogate":false,"dq":false},{"teamNumber":2642,"station":"Red3","surrogate":false,"dq":false},{"teamNumber":5323,"station":"Blue1","surrogate":false,"dq":false},{"teamNumber":1413,"station":"Blue2","surrogate":false,"dq":false},{"teamNumber":3196,"station":"Blue3","surrogate":false,"dq":false}]},{"description":"Qualification 59","tournamentLevel":"Qualification","matchNumber":59,"startTime":"2015-03-20T17:01:00","actualStartTime":"2015-03-20T17:14:53.407","scoreRedFinal":72,"scoreRedFoul":0,"scoreRedAuto":0,"scoreBlueFinal":64,"scoreBlueFoul":0,"scoreBlueAuto":0,"Teams":[{"teamNumber":5190,"station":"Red1","surrogate":false,"dq":false},{"teamNumber":435,"station":"Red2","surrogate":false,"dq":false},{"teamNumber":5679,"station":"Red3","surrogate":false,"dq":false},{"teamNumber":587,"station":"Blue1","surrogate":false,"dq":false},{"teamNumber":4829,"station":"Blue2","surrogate":false,"dq":false},{"teamNumber":5727,"station":"Blue3","surrogate":false,"dq":false}]},{"description":"Qualification 60","tournamentLevel":"Qualification","matchNumber":60,"startTime":"2015-03-20T17:08:00","actualStartTime":"2015-03-20T17:21:06.317","scoreRedFinal":4,"scoreRedFoul":0,"scoreRedAuto":0,"scoreBlueFinal":51,"scoreBlueFoul":0,"scoreBlueAuto":0,"Teams":[{"teamNumber":3680,"station":"Red1","surrogate":false,"dq":false},{"teamNumber":3737,"station":"Red2","surrogate":false,"dq":false},{"teamNumber":5543,"station":"Red3","surrogate":false,"dq":false},{"teamNumber":3459,"station":"Blue1","surrogate":false,"dq":false},{"teamNumber":2059,"station":"Blue2","surrogate":false,"dq":false},{"teamNumber":3506,"station":"Blue3","surrogate":false,"dq":false}]},{"description":"Qualification 61","tournamentLevel":"Qualification","matchNumber":61,"startTime":"2015-03-20T17:15:00","actualStartTime":"2015-03-20T17:27:23.92","scoreRedFinal":8,"scoreRedFoul":0,"scoreRedAuto":0,"scoreBlueFinal":46,"scoreBlueFoul":0,"scoreBlueAuto":0,"Teams":[{"teamNumber":4828,"station":"Red1","surrogate":false,"dq":false},{"teamNumber":2890,"station":"Red2","surrogate":false,"dq":false},{"teamNumber":5762,"station":"Red3","surrogate":false,"dq":false},{"teamNumber":3845,"station":"Blue1","surrogate":false,"dq":false},{"teamNumber":3215,"station":"Blue2","surrogate":false,"dq":false},{"teamNumber":2640,"station":"Blue3","surrogate":false,"dq":false}]},{"description":"Qualification 62","tournamentLevel":"Qualification","matchNumber":62,"startTime":"2015-03-20T17:22:00","actualStartTime":"2015-03-20T17:33:43.047","scoreRedFinal":24,"scoreRedFoul":0,"scoreRedAuto":0,"scoreBlueFinal":26,"scoreBlueFoul":6,"scoreBlueAuto":0,"Teams":[{"teamNumber":3822,"station":"Red1","surrogate":false,"dq":false},{"teamNumber":4795,"station":"Red2","surrogate":false,"dq":false},{"teamNumber":3229,"station":"Red3","surrogate":false,"dq":false},{"teamNumber":5446,"station":"Blue1","surrogate":false,"dq":false},{"teamNumber":3763,"station":"Blue2","surrogate":false,"dq":false},{"teamNumber":5607,"station":"Blue3","surrogate":false,"dq":false}]},{"description":"Qualification 63","tournamentLevel":"Qualification","matchNumber":63,"startTime":"2015-03-20T17:29:00","actualStartTime":"2015-03-20T18:11:37.077","scoreRedFinal":42,"scoreRedFoul":0,"scoreRedAuto":0,"scoreBlueFinal":14,"scoreBlueFoul":0,"scoreBlueAuto":0,"Teams":[{"teamNumber":3336,"station":"Red1","surrogate":false,"dq":false},{"teamNumber":4767,"station":"Red2","surrogate":false,"dq":false},{"teamNumber":2528,"station":"Red3","surrogate":false,"dq":false},{"teamNumber":4534,"station":"Blue1","surrogate":false,"dq":false},{"teamNumber":3331,"station":"Blue2","surrogate":false,"dq":false},{"teamNumber":3270,"station":"Blue3","surrogate":false,"dq":false}]},{"description":"Qualification 64","tournamentLevel":"Qualification","matchNumber":64,"startTime":"2015-03-20T17:36:00","actualStartTime":"2015-03-20T18:17:37.4","scoreRedFinal":63,"scoreRedFoul":6,"scoreRedAuto":0,"scoreBlueFinal":56,"scoreBlueFoul":6,"scoreBlueAuto":0,"Teams":[{"teamNumber":4290,"station":"Red1","surrogate":false,"dq":false},{"teamNumber":3402,"station":"Red2","surrogate":false,"dq":false},{"teamNumber":5518,"station":"Red3","surrogate":false,"dq":false},{"teamNumber":4996,"station":"Blue1","surrogate":false,"dq":false},{"teamNumber":1533,"station":"Blue2","surrogate":false,"dq":false},{"teamNumber":5160,"station":"Blue3","surrogate":false,"dq":false}]},{"description":"Qualification 65","tournamentLevel":"Qualification","matchNumber":65,"startTime":"2015-03-21T09:00:00","actualStartTime":"2015-03-21T08:57:07.323","scoreRedFinal":46,"scoreRedFoul":0,"scoreRedAuto":0,"scoreBlueFinal":0,"scoreBlueFoul":0,"scoreBlueAuto":0,"Teams":[{"teamNumber":2641,"station":"Red1","surrogate":false,"dq":false},{"teamNumber":3680,"station":"Red2","surrogate":false,"dq":false},{"teamNumber":1225,"station":"Red3","surrogate":false,"dq":false},{"teamNumber":5323,"station":"Blue1","surrogate":false,"dq":false},{"teamNumber":4829,"station":"Blue2","surrogate":false,"dq":false},{"teamNumber":4291,"station":"Blue3","surrogate":false,"dq":false}]},{"description":"Qualification 66","tournamentLevel":"Qualification","matchNumber":66,"startTime":"2015-03-21T09:07:00","actualStartTime":"2015-03-21T09:03:31.027","scoreRedFinal":28,"scoreRedFoul":0,"scoreRedAuto":0,"scoreBlueFinal":42,"scoreBlueFoul":0,"scoreBlueAuto":0,"Teams":[{"teamNumber":3845,"station":"Red1","surrogate":false,"dq":false},{"teamNumber":4533,"station":"Red2","surrogate":false,"dq":false},{"teamNumber":5544,"station":"Red3","surrogate":false,"dq":false},{"teamNumber":2890,"station":"Blue1","surrogate":false,"dq":false},{"teamNumber":5679,"station":"Blue2","surrogate":false,"dq":false},{"teamNumber":3459,"station":"Blue3","surrogate":false,"dq":false}]},{"description":"Qualification 67","tournamentLevel":"Qualification","matchNumber":67,"startTime":"2015-03-21T09:14:00","actualStartTime":"2015-03-21T09:09:49.75","scoreRedFinal":33,"scoreRedFoul":0,"scoreRedAuto":0,"scoreBlueFinal":43,"scoreBlueFoul":6,"scoreBlueAuto":0,"Teams":[{"teamNumber":4561,"station":"Red1","surrogate":false,"dq":false},{"teamNumber":3701,"station":"Red2","surrogate":false,"dq":false},{"teamNumber":900,"station":"Red3","surrogate":false,"dq":false},{"teamNumber":3971,"station":"Blue1","surrogate":false,"dq":false},{"teamNumber":5543,"station":"Blue2","surrogate":false,"dq":false},{"teamNumber":3763,"station":"Blue3","surrogate":false,"dq":false}]},{"description":"Qualification 68","tournamentLevel":"Qualification","matchNumber":68,"startTime":"2015-03-21T09:21:00","actualStartTime":"2015-03-21T09:15:53.403","scoreRedFinal":10,"scoreRedFoul":12,"scoreRedAuto":0,"scoreBlueFinal":41,"scoreBlueFoul":0,"scoreBlueAuto":0,"Teams":[{"teamNumber":2059,"station":"Red1","surrogate":false,"dq":false},{"teamNumber":1413,"station":"Red2","surrogate":false,"dq":false},{"teamNumber":5190,"station":"Red3","surrogate":false,"dq":false},{"teamNumber":4073,"station":"Blue1","surrogate":false,"dq":false},{"teamNumber":3229,"station":"Blue2","surrogate":false,"dq":false},{"teamNumber":3196,"station":"Blue3","surrogate":false,"dq":false}]},{"description":"Qualification 69","tournamentLevel":"Qualification","matchNumber":69,"startTime":"2015-03-21T09:28:00","actualStartTime":"2015-03-21T09:22:55.187","scoreRedFinal":2,"scoreRedFoul":0,"scoreRedAuto":0,"scoreBlueFinal":6,"scoreBlueFoul":0,"scoreBlueAuto":0,"Teams":[{"teamNumber":435,"station":"Red1","surrogate":false,"dq":false},{"teamNumber":3661,"station":"Red2","surrogate":false,"dq":false},{"teamNumber":3215,"station":"Red3","surrogate":false,"dq":false},{"teamNumber":5607,"station":"Blue1","surrogate":false,"dq":false},{"teamNumber":3331,"station":"Blue2","surrogate":false,"dq":false},{"teamNumber":4996,"station":"Blue3","surrogate":false,"dq":false}]},{"description":"Qualification 70","tournamentLevel":"Qualification","matchNumber":70,"startTime":"2015-03-21T09:35:00","actualStartTime":"2015-03-21T09:41:06.077","scoreRedFinal":51,"scoreRedFoul":0,"scoreRedAuto":0,"scoreBlueFinal":52,"scoreBlueFoul":0,"scoreBlueAuto":0,"Teams":[{"teamNumber":3336,"station":"Red1","surrogate":false,"dq":false},{"teamNumber":5511,"station":"Red2","surrogate":false,"dq":false},{"teamNumber":3270,"station":"Red3","surrogate":false,"dq":false},{"teamNumber":5762,"station":"Blue1","surrogate":false,"dq":false},{"teamNumber":3737,"station":"Blue2","surrogate":false,"dq":false},{"teamNumber":2642,"station":"Blue3","surrogate":false,"dq":false}]},{"description":"Qualification 71","tournamentLevel":"Qualification","matchNumber":71,"startTime":"2015-03-21T09:42:00","actualStartTime":"2015-03-21T09:48:08.58","scoreRedFinal":37,"scoreRedFoul":0,"scoreRedAuto":0,"scoreBlueFinal":68,"scoreBlueFoul":6,"scoreBlueAuto":0,"Teams":[{"teamNumber":5446,"station":"Red1","surrogate":false,"dq":false},{"teamNumber":3796,"station":"Red2","surrogate":false,"dq":false},{"teamNumber":4795,"station":"Red3","surrogate":false,"dq":false},{"teamNumber":3402,"station":"Blue1","surrogate":false,"dq":false},{"teamNumber":4767,"station":"Blue2","surrogate":false,"dq":false},{"teamNumber":3506,"station":"Blue3","surrogate":false,"dq":false}]},{"description":"Qualification 72","tournamentLevel":"Qualification","matchNumber":72,"startTime":"2015-03-21T09:49:00","actualStartTime":"2015-03-21T09:54:41.43","scoreRedFinal":24,"scoreRedFoul":0,"scoreRedAuto":0,"scoreBlueFinal":26,"scoreBlueFoul":0,"scoreBlueAuto":0,"Teams":[{"teamNumber":3822,"station":"Red1","surrogate":false,"dq":false},{"teamNumber":5518,"station":"Red2","surrogate":false,"dq":false},{"teamNumber":4534,"station":"Red3","surrogate":false,"dq":false},{"teamNumber":587,"station":"Blue1","surrogate":false,"dq":false},{"teamNumber":4828,"station":"Blue2","surrogate":false,"dq":false},{"teamNumber":4290,"station":"Blue3","surrogate":false,"dq":false}]},{"description":"Qualification 73","tournamentLevel":"Qualification","matchNumber":73,"startTime":"2015-03-21T09:56:00","actualStartTime":"2015-03-21T10:00:19.113","scoreRedFinal":21,"scoreRedFoul":0,"scoreRedAuto":0,"scoreBlueFinal":16,"scoreBlueFoul":0,"scoreBlueAuto":0,"Teams":[{"teamNumber":5727,"station":"Red1","surrogate":false,"dq":false},{"teamNumber":1533,"station":"Red2","surrogate":false,"dq":false},{"teamNumber":2640,"station":"Red3","surrogate":false,"dq":false},{"teamNumber":4816,"station":"Blue1","surrogate":false,"dq":false},{"teamNumber":2682,"station":"Blue2","surrogate":false,"dq":false},{"teamNumber":2641,"station":"Blue3","surrogate":false,"dq":false}]},{"description":"Qualification 74","tournamentLevel":"Qualification","matchNumber":74,"startTime":"2015-03-21T10:03:00","actualStartTime":"2015-03-21T12:44:56.757","scoreRedFinal":26,"scoreRedFoul":0,"scoreRedAuto":0,"scoreBlueFinal":57,"scoreBlueFoul":0,"scoreBlueAuto":0,"Teams":[{"teamNumber":2528,"station":"Red1","surrogate":false,"dq":false},{"teamNumber":5543,"station":"Red2","surrogate":false,"dq":false},{"teamNumber":3845,"station":"Red3","surrogate":false,"dq":false},{"teamNumber":5160,"station":"Blue1","surrogate":false,"dq":false},{"teamNumber":5544,"station":"Blue2","surrogate":false,"dq":false},{"teamNumber":3680,"station":"Blue3","surrogate":false,"dq":false}]},{"description":"Qualification 75","tournamentLevel":"Qualification","matchNumber":75,"startTime":"2015-03-21T10:10:00","actualStartTime":"2015-03-21T10:21:33.693","scoreRedFinal":31,"scoreRedFoul":6,"scoreRedAuto":6,"scoreBlueFinal":29,"scoreBlueFoul":0,"scoreBlueAuto":0,"Teams":[{"teamNumber":4829,"station":"Red1","surrogate":false,"dq":false},{"teamNumber":3661,"station":"Red2","surrogate":false,"dq":false},{"teamNumber":4996,"station":"Red3","surrogate":false,"dq":false},{"teamNumber":3336,"station":"Blue1","surrogate":false,"dq":false},{"teamNumber":3971,"station":"Blue2","surrogate":false,"dq":false},{"teamNumber":5762,"station":"Blue3","surrogate":false,"dq":false}]},{"description":"Qualification 76","tournamentLevel":"Qualification","matchNumber":76,"startTime":"2015-03-21T10:17:00","actualStartTime":"2015-03-21T12:50:55.457","scoreRedFinal":78,"scoreRedFoul":0,"scoreRedAuto":0,"scoreBlueFinal":50,"scoreBlueFoul":6,"scoreBlueAuto":0,"Teams":[{"teamNumber":5190,"station":"Red1","surrogate":false,"dq":false},{"teamNumber":3506,"station":"Red2","surrogate":false,"dq":false},{"teamNumber":3331,"station":"Red3","surrogate":false,"dq":false},{"teamNumber":1225,"station":"Blue1","surrogate":false,"dq":false},{"teamNumber":2890,"station":"Blue2","surrogate":false,"dq":false},{"teamNumber":5323,"station":"Blue3","surrogate":false,"dq":false}]},{"description":"Qualification 77","tournamentLevel":"Qualification","matchNumber":77,"startTime":"2015-03-21T10:24:00","actualStartTime":"2015-03-21T10:34:28.413","scoreRedFinal":32,"scoreRedFoul":0,"scoreRedAuto":0,"scoreBlueFinal":47,"scoreBlueFoul":0,"scoreBlueAuto":0,"Teams":[{"teamNumber":3737,"station":"Red1","surrogate":false,"dq":false},{"teamNumber":587,"station":"Red2","surrogate":false,"dq":false},{"teamNumber":2059,"station":"Red3","surrogate":false,"dq":false},{"teamNumber":4561,"station":"Blue1","surrogate":false,"dq":false},{"teamNumber":5446,"station":"Blue2","surrogate":false,"dq":false},{"teamNumber":5518,"station":"Blue3","surrogate":false,"dq":false}]},{"description":"Qualification 78","tournamentLevel":"Qualification","matchNumber":78,"startTime":"2015-03-21T10:31:00","actualStartTime":"2015-03-21T10:40:30.07","scoreRedFinal":16,"scoreRedFoul":0,"scoreRedAuto":0,"scoreBlueFinal":31,"scoreBlueFoul":6,"scoreBlueAuto":0,"Teams":[{"teamNumber":2640,"station":"Red1","surrogate":false,"dq":false},{"teamNumber":3196,"station":"Red2","surrogate":false,"dq":false},{"teamNumber":3796,"station":"Red3","surrogate":false,"dq":false},{"teamNumber":4073,"station":"Blue1","surrogate":false,"dq":false},{"teamNumber":435,"station":"Blue2","surrogate":false,"dq":false},{"teamNumber":5607,"station":"Blue3","surrogate":false,"dq":false}]},{"description":"Qualification 79","tournamentLevel":"Qualification","matchNumber":79,"startTime":"2015-03-21T10:38:00","actualStartTime":"2015-03-21T10:46:14.607","scoreRedFinal":35,"scoreRedFoul":0,"scoreRedAuto":0,"scoreBlueFinal":22,"scoreBlueFoul":6,"scoreBlueAuto":0,"Teams":[{"teamNumber":4290,"station":"Red1","surrogate":false,"dq":false},{"teamNumber":3763,"station":"Red2","surrogate":false,"dq":false},{"teamNumber":4534,"station":"Red3","surrogate":false,"dq":false},{"teamNumber":5160,"station":"Blue1","surrogate":false,"dq":false},{"teamNumber":2641,"station":"Blue2","surrogate":false,"dq":false},{"teamNumber":3270,"station":"Blue3","surrogate":false,"dq":false}]},{"description":"Qualification 80","tournamentLevel":"Qualification","matchNumber":80,"startTime":"2015-03-21T10:45:00","actualStartTime":"2015-03-21T10:56:33.227","scoreRedFinal":0,"scoreRedFoul":12,"scoreRedAuto":0,"scoreBlueFinal":27,"scoreBlueFoul":0,"scoreBlueAuto":0,"Teams":[{"teamNumber":4816,"station":"Red1","surrogate":false,"dq":false},{"teamNumber":5511,"station":"Red2","surrogate":false,"dq":false},{"teamNumber":5727,"station":"Red3","surrogate":false,"dq":false},{"teamNumber":900,"station":"Blue1","surrogate":false,"dq":false},{"teamNumber":2528,"station":"Blue2","surrogate":false,"dq":false},{"teamNumber":4291,"station":"Blue3","surrogate":false,"dq":false}]},{"description":"Qualification 81","tournamentLevel":"Qualification","matchNumber":81,"startTime":"2015-03-21T10:52:00","actualStartTime":"2015-03-21T11:02:43.01","scoreRedFinal":42,"scoreRedFoul":0,"scoreRedAuto":0,"scoreBlueFinal":48,"scoreBlueFoul":0,"scoreBlueAuto":0,"Teams":[{"teamNumber":4828,"station":"Red1","surrogate":false,"dq":false},{"teamNumber":3701,"station":"Red2","surrogate":false,"dq":false},{"teamNumber":1413,"station":"Red3","surrogate":false,"dq":false},{"teamNumber":3402,"station":"Blue1","surrogate":false,"dq":false},{"teamNumber":4795,"station":"Blue2","surrogate":false,"dq":false},{"teamNumber":4533,"station":"Blue3","surrogate":false,"dq":false}]},{"description":"Qualification 82","tournamentLevel":"Qualification","matchNumber":82,"startTime":"2015-03-21T10:59:00","actualStartTime":"2015-03-21T11:09:03.983","scoreRedFinal":43,"scoreRedFoul":0,"scoreRedAuto":0,"scoreBlueFinal":44,"scoreBlueFoul":0,"scoreBlueAuto":0,"Teams":[{"teamNumber":3822,"station":"Red1","surrogate":false,"dq":false},{"teamNumber":2642,"station":"Red2","surrogate":false,"dq":false},{"teamNumber":4767,"station":"Red3","surrogate":false,"dq":false},{"teamNumber":3459,"station":"Blue1","surrogate":false,"dq":false},{"teamNumber":3215,"station":"Blue2","surrogate":false,"dq":false},{"teamNumber":1533,"station":"Blue3","surrogate":false,"dq":false}]},{"description":"Qualification 83","tournamentLevel":"Qualification","matchNumber":83,"startTime":"2015-03-21T11:06:00","actualStartTime":"2015-03-21T11:16:05.61","scoreRedFinal":52,"scoreRedFoul":0,"scoreRedAuto":0,"scoreBlueFinal":32,"scoreBlueFoul":0,"scoreBlueAuto":0,"Teams":[{"teamNumber":2682,"station":"Red1","surrogate":false,"dq":false},{"teamNumber":5679,"station":"Red2","surrogate":false,"dq":false},{"teamNumber":5518,"station":"Red3","surrogate":false,"dq":false},{"teamNumber":3229,"station":"Blue1","surrogate":false,"dq":false},{"teamNumber":5762,"station":"Blue2","surrogate":false,"dq":false},{"teamNumber":3506,"station":"Blue3","surrogate":false,"dq":false}]},{"description":"Qualification 84","tournamentLevel":"Qualification","matchNumber":84,"startTime":"2015-03-21T11:13:00","actualStartTime":"2015-03-21T11:25:36.127","scoreRedFinal":84,"scoreRedFoul":0,"scoreRedAuto":0,"scoreBlueFinal":47,"scoreBlueFoul":0,"scoreBlueAuto":0,"Teams":[{"teamNumber":3336,"station":"Red1","surrogate":false,"dq":false},{"teamNumber":1225,"station":"Red2","surrogate":false,"dq":false},{"teamNumber":2640,"station":"Red3","surrogate":false,"dq":false},{"teamNumber":587,"station":"Blue1","surrogate":false,"dq":false},{"teamNumber":3796,"station":"Blue2","surrogate":false,"dq":false},{"teamNumber":3270,"station":"Blue3","surrogate":false,"dq":false}]},{"description":"Qualification 85","tournamentLevel":"Qualification","matchNumber":85,"startTime":"2015-03-21T11:20:00","actualStartTime":"2015-03-21T11:32:39.977","scoreRedFinal":18,"scoreRedFoul":0,"scoreRedAuto":0,"scoreBlueFinal":60,"scoreBlueFoul":0,"scoreBlueAuto":0,"Teams":[{"teamNumber":2641,"station":"Red1","surrogate":false,"dq":false},{"teamNumber":5323,"station":"Red2","surrogate":false,"dq":false},{"teamNumber":4996,"station":"Red3","surrogate":false,"dq":false},{"teamNumber":2528,"station":"Blue1","surrogate":false,"dq":false},{"teamNumber":5160,"station":"Blue2","surrogate":false,"dq":false},{"teamNumber":4073,"station":"Blue3","surrogate":false,"dq":false}]},{"description":"Qualification 86","tournamentLevel":"Qualification","matchNumber":86,"startTime":"2015-03-21T11:27:00","actualStartTime":"2015-03-21T11:38:49.1","scoreRedFinal":57,"scoreRedFoul":0,"scoreRedAuto":0,"scoreBlueFinal":38,"scoreBlueFoul":0,"scoreBlueAuto":0,"Teams":[{"teamNumber":4534,"station":"Red1","surrogate":false,"dq":false},{"teamNumber":4533,"station":"Red2","surrogate":false,"dq":false},{"teamNumber":5543,"station":"Red3","surrogate":false,"dq":false},{"teamNumber":5190,"station":"Blue1","surrogate":false,"dq":false},{"teamNumber":4816,"station":"Blue2","surrogate":false,"dq":false},{"teamNumber":3763,"station":"Blue3","surrogate":false,"dq":false}]},{"description":"Qualification 87","tournamentLevel":"Qualification","matchNumber":87,"startTime":"2015-03-21T11:34:00","actualStartTime":"2015-03-21T11:46:39.327","scoreRedFinal":25,"scoreRedFoul":12,"scoreRedAuto":0,"scoreBlueFinal":28,"scoreBlueFoul":0,"scoreBlueAuto":0,"Teams":[{"teamNumber":5607,"station":"Red1","surrogate":false,"dq":false},{"teamNumber":2642,"station":"Red2","surrogate":false,"dq":false},{"teamNumber":3661,"station":"Red3","surrogate":false,"dq":false},{"teamNumber":5544,"station":"Blue1","surrogate":false,"dq":false},{"teamNumber":5446,"station":"Blue2","surrogate":false,"dq":false},{"teamNumber":3701,"station":"Blue3","surrogate":false,"dq":false}]},{"description":"Qualification 88","tournamentLevel":"Qualification","matchNumber":88,"startTime":"2015-03-21T11:41:00","actualStartTime":"2015-03-21T11:52:58.66","scoreRedFinal":36,"scoreRedFoul":0,"scoreRedAuto":0,"scoreBlueFinal":14,"scoreBlueFoul":0,"scoreBlueAuto":0,"Teams":[{"teamNumber":4290,"station":"Red1","surrogate":false,"dq":false},{"teamNumber":3215,"station":"Red2","surrogate":false,"dq":false},{"teamNumber":2682,"station":"Red3","surrogate":false,"dq":false},{"teamNumber":4829,"station":"Blue1","surrogate":false,"dq":false},{"teamNumber":4795,"station":"Blue2","surrogate":false,"dq":false},{"teamNumber":3737,"station":"Blue3","surrogate":false,"dq":false}]},{"description":"Qualification 89","tournamentLevel":"Qualification","matchNumber":89,"startTime":"2015-03-21T11:48:00","actualStartTime":"2015-03-21T11:59:48.52","scoreRedFinal":51,"scoreRedFoul":0,"scoreRedAuto":0,"scoreBlueFinal":14,"scoreBlueFoul":0,"scoreBlueAuto":0,"Teams":[{"teamNumber":900,"station":"Red1","surrogate":false,"dq":false},{"teamNumber":3229,"station":"Red2","surrogate":false,"dq":false},{"teamNumber":1533,"station":"Red3","surrogate":false,"dq":false},{"teamNumber":2890,"station":"Blue1","surrogate":false,"dq":false},{"teamNumber":435,"station":"Blue2","surrogate":false,"dq":false},{"teamNumber":3680,"station":"Blue3","surrogate":false,"dq":false}]},{"description":"Qualification 90","tournamentLevel":"Qualification","matchNumber":90,"startTime":"2015-03-21T11:55:00","actualStartTime":"2015-03-21T12:06:13.86","scoreRedFinal":29,"scoreRedFoul":0,"scoreRedAuto":0,"scoreBlueFinal":21,"scoreBlueFoul":0,"scoreBlueAuto":0,"Teams":[{"teamNumber":3402,"station":"Red1","surrogate":false,"dq":false},{"teamNumber":3196,"station":"Red2","surrogate":false,"dq":false},{"teamNumber":5727,"station":"Red3","surrogate":false,"dq":false},{"teamNumber":4767,"station":"Blue1","surrogate":false,"dq":false},{"teamNumber":4561,"station":"Blue2","surrogate":false,"dq":false},{"teamNumber":3845,"station":"Blue3","surrogate":false,"dq":false}]},{"description":"Qualification 91","tournamentLevel":"Qualification","matchNumber":91,"startTime":"2015-03-21T12:02:00","actualStartTime":"2015-03-21T12:14:37.527","scoreRedFinal":25,"scoreRedFoul":0,"scoreRedAuto":0,"scoreBlueFinal":35,"scoreBlueFoul":0,"scoreBlueAuto":0,"Teams":[{"teamNumber":4828,"station":"Red1","surrogate":false,"dq":false},{"teamNumber":3459,"station":"Red2","surrogate":false,"dq":false},{"teamNumber":4291,"station":"Red3","surrogate":false,"dq":false},{"teamNumber":3971,"station":"Blue1","surrogate":false,"dq":false},{"teamNumber":5679,"station":"Blue2","surrogate":false,"dq":false},{"teamNumber":3331,"station":"Blue3","surrogate":false,"dq":false}]},{"description":"Qualification 92","tournamentLevel":"Qualification","matchNumber":92,"startTime":"2015-03-21T12:09:00","actualStartTime":"2015-03-21T12:21:02.067","scoreRedFinal":116,"scoreRedFoul":0,"scoreRedAuto":0,"scoreBlueFinal":101,"scoreBlueFoul":0,"scoreBlueAuto":0,"Teams":[{"teamNumber":5511,"station":"Red1","surrogate":false,"dq":false},{"teamNumber":2059,"station":"Red2","surrogate":false,"dq":false},{"teamNumber":1225,"station":"Red3","surrogate":false,"dq":false},{"teamNumber":3822,"station":"Blue1","surrogate":false,"dq":false},{"teamNumber":1413,"station":"Blue2","surrogate":false,"dq":false},{"teamNumber":3336,"station":"Blue3","surrogate":false,"dq":false}]}]}